tablefill/__init__.py
tablefill/cli.py
tablefill/server.py
tablefill/src.py
tablefill-0.2.0.dist-info/entry_points.txt
tablefill-0.2.0.dist-info/LICENSE
tablefill-0.2.0.dist-info/WHEEL
tablefill-0.2.0.dist-info/METADATA
tablefill-0.2.0.dist-info/RECORD
