Metadata-Version: 2.1
Name: tablefill
Version: 0.2.0
Summary: Excel模板数据填充,快速应对Web项目数据导入
Home-page: https://gitee.com/zy7y/tablefill
License: MIT
Keywords: excel,data,test
Author: 柒意
Author-email: 396667207@qq.com
Requires-Python: >=3.9,<4.0
Classifier: License :: OSI Approved :: MIT License
Classifier: Programming Language :: Python :: 3
Classifier: Programming Language :: Python :: 3.10
Classifier: Programming Language :: Python :: 3.9
Requires-Dist: Faker (>=8.14.0,<9.0.0)
Requires-Dist: rich (>=10.16.2,<11.0.0)
Requires-Dist: typer (>=0.4.0,<0.5.0)
Requires-Dist: xlrd (==1.2.0)
Requires-Dist: xlutils (==2.0.0)
Project-URL: Repository, https://github.com/zy7y/tablefill
